[{"lx":90,"ly":114,"mx":90,"my":113},{"lx":90,"ly":113,"mx":90,"my":114},{"lx":90,"ly":114,"mx":90,"my":113},{"lx":90,"ly":113,"mx":90,"my":114},{"lx":90,"ly":114,"mx":90,"my":113},{"lx":90,"ly":115,"mx":90,"my":114},{"lx":89,"ly":115,"mx":90,"my":115},{"lx":88,"ly":115,"mx":89,"my":115},{"lx":85,"ly":114,"mx":88,"my":115},{"lx":83,"ly":113,"mx":85,"my":114},{"lx":81,"ly":113,"mx":83,"my":113},{"lx":77,"ly":111,"mx":81,"my":113},{"lx":63,"ly":110,"mx":77,"my":111},{"lx":61,"ly":110,"mx":63,"my":110},{"lx":60,"ly":110,"mx":61,"my":110},{"lx":59,"ly":109,"mx":60,"my":110},{"lx":63,"ly":109,"mx":59,"my":109},{"lx":72,"ly":109,"mx":63,"my":109},{"lx":108,"ly":109,"mx":72,"my":109},{"lx":160,"ly":109,"mx":108,"my":109},{"lx":192,"ly":109,"mx":160,"my":109},{"lx":215,"ly":108,"mx":192,"my":109},{"lx":217,"ly":108,"mx":215,"my":108},{"lx":218,"ly":108,"mx":217,"my":108},{"lx":219,"ly":108,"mx":218,"my":108},{"lx":218,"ly":108,"mx":219,"my":108},{"lx":214,"ly":108,"mx":218,"my":108},{"lx":206,"ly":108,"mx":214,"my":108},{"lx":140,"ly":108,"mx":206,"my":108},{"lx":123,"ly":108,"mx":140,"my":108},{"lx":111,"ly":108,"mx":123,"my":108},{"lx":104,"ly":108,"mx":111,"my":108},{"lx":103,"ly":107,"mx":104,"my":108},{"lx":102,"ly":107,"mx":103,"my":107},{"lx":102,"ly":106,"mx":102,"my":107},{"lx":102,"ly":105,"mx":102,"my":106},{"lx":102,"ly":104,"mx":102,"my":105},{"lx":100,"ly":102,"mx":102,"my":104},{"lx":98,"ly":101,"mx":100,"my":102},{"lx":93,"ly":98,"mx":98,"my":101},{"lx":91,"ly":96,"mx":93,"my":98},{"lx":90,"ly":95,"mx":91,"my":96},{"lx":89,"ly":94,"mx":90,"my":95},{"lx":89,"ly":93,"mx":89,"my":94},{"lx":89,"ly":92,"mx":89,"my":93},{"lx":89,"ly":91,"mx":89,"my":92},{"lx":93,"ly":91,"mx":89,"my":91},{"lx":101,"ly":91,"mx":93,"my":91},{"lx":106,"ly":91,"mx":101,"my":91},{"lx":109,"ly":91,"mx":106,"my":91},{"lx":113,"ly":91,"mx":109,"my":91},{"lx":119,"ly":92,"mx":113,"my":91},{"lx":123,"ly":92,"mx":119,"my":92},{"lx":131,"ly":92,"mx":123,"my":92},{"lx":136,"ly":92,"mx":131,"my":92},{"lx":141,"ly":93,"mx":136,"my":92},{"lx":142,"ly":93,"mx":141,"my":93},{"lx":143,"ly":93,"mx":142,"my":93},{"lx":146,"ly":93,"mx":143,"my":93},{"lx":147,"ly":93,"mx":146,"my":93},{"lx":148,"ly":93,"mx":147,"my":93}]